pyloopenergy/__init__.py
pyloopenergy/loop_energy.py
pyloopenergy-0.2.1.dist-info/WHEEL
pyloopenergy-0.2.1.dist-info/METADATA
pyloopenergy-0.2.1.dist-info/RECORD
