Metadata-Version: 2.1
Name: pyloopenergy
Version: 0.2.1
Summary: Access Loop Energy energy monitors via Socket.IO API
Home-page: http://github.com/pavoni/pyloopenergy
License: MIT
Keywords: loopenergy,api
Author: Greg Dowling
Author-email: mail@gregdowling.com
Requires-Python: >=3.6,<4.0
Classifier: License :: OSI Approved :: MIT License
Classifier: Programming Language :: Python :: 3
Classifier: Programming Language :: Python :: 3.6
Classifier: Programming Language :: Python :: 3.7
Classifier: Programming Language :: Python :: 3.8
Requires-Dist: python-socketio (>=v4.6.0)
Requires-Dist: requests (>=2.0)
Project-URL: Repository, http://github.com/pavoni/pyloopenergy
